LICENSE
README.md
setup.py
jko_api_utils/BatchAPIController.py
jko_api_utils/__init__.py
jko_api_utils.egg-info/PKG-INFO
jko_api_utils.egg-info/SOURCES.txt
jko_api_utils.egg-info/dependency_links.txt
jko_api_utils.egg-info/top_level.txt
jko_api_utils/google/__init__.py
jko_api_utils/google/drive/__init__.py
jko_api_utils/google/drive/download/__init__.py
jko_api_utils/google/drive/download/main.py
jko_api_utils/google/drive/service/__init__.py
jko_api_utils/google/drive/service/get_service.py
jko_api_utils/replicate/__init__.py
jko_api_utils/replicate/whisper/__init__.py
jko_api_utils/replicate/whisper/main.py
jko_api_utils/utils/__init__.py
jko_api_utils/utils/api.py
tests/__init__.py
tests/test_save_data.py
tests/utils/__init__.py
tests/utils/test_convert_data_to_string.py
tests/utils/test_create_dirs_if_needed.py
tests/utils/test_handle_duplicate_paths.py
tests/utils/test_save_data.py
tests/utils/test_save_data_to_file.py