Metadata-Version: 2.1
Name: jko-api-utils
Version: 0.1.2
Summary: Utility functions for working with APIs
License-File: LICENSE
